juntagrico_webdav/__init__.py
juntagrico_webdav/admin.py
juntagrico_webdav/apps.py
juntagrico_webdav/models.py
juntagrico_webdav/urls.py
juntagrico_webdav/views.py
juntagrico_webdav/migrations/0001_initial.py
juntagrico_webdav/migrations/0002_auto_20191111_1501.py
juntagrico_webdav/migrations/__init__.py
juntagrico_webdav/templates/juntagrico/menu/admin.html
juntagrico_webdav/templates/juntagrico/menu/user.html
juntagrico_webdav/templates/wd/list.html
juntagrico_webdav/templatetags/__init__.py
juntagrico_webdav/templatetags/juntagrico_webdav/__init__.py
juntagrico_webdav/templatetags/juntagrico_webdav/menus.py
juntagrico_webdav-1.7.0.dist-info/licenses/LICENSE
juntagrico_webdav-1.7.0.dist-info/METADATA
juntagrico_webdav-1.7.0.dist-info/WHEEL
juntagrico_webdav-1.7.0.dist-info/top_level.txt
juntagrico_webdav-1.7.0.dist-info/RECORD
