Metadata-Version: 2.4
Name: juntagrico-webdav
Version: 1.7.0
Summary: Include webdav folders into juntagrico to share files with your members.
Author-email: juntagrico <python@juntagrico.org>
License:                    GNU LESSER GENERAL PUBLIC LICENSE
Project-URL: Homepage, https://www.juntagrico.org
Project-URL: Issues, https://github.com/juntagrico/juntagrico-webdav/issues
Classifier: Development Status :: 5 - Production/Stable
Classifier: Environment :: Web Environment
Classifier: Framework :: Django
Classifier: Framework :: Django :: 4.2
Classifier: Intended Audience :: Developers
Classifier: Intended Audience :: Other Audience
Classifier: License :: OSI Approved :: GNU Lesser General Public License v3 (LGPLv3)
Classifier: Operating System :: OS Independent
Classifier: Programming Language :: Python
Classifier: Programming Language :: Python :: 3.9
Classifier: Programming Language :: Python :: 3.10
Classifier: Programming Language :: Python :: 3.11
Classifier: Topic :: Internet :: WWW/HTTP :: Site Management
Requires-Python: >=3.9
License-File: LICENSE
Requires-Dist: juntagrico>=1.7.0
Requires-Dist: dateparser>=1.1.4
Requires-Dist: requests>=2.31.0
Requires-Dist: lxml>=4.6.3
Dynamic: license-file
